phamclust/__init__.py
phamclust/__main__.py
phamclust/cli.py
phamclust/clustering.py
phamclust/fasta.py
phamclust/genome.py
phamclust/heatmap.py
phamclust/matrix.py
phamclust/metrics.py
phamclust/parallel_process.py
phamclust/statistics.py
phamclust/scripts/__init__.py
phamclust/scripts/benchmark.py
phamclust/scripts/nucclust.py
phamclust/scripts/phamclust.py
phamclust-1.3.3.dist-info/LICENSE
phamclust-1.3.3.dist-info/METADATA
phamclust-1.3.3.dist-info/WHEEL
phamclust-1.3.3.dist-info/entry_points.txt
phamclust-1.3.3.dist-info/top_level.txt
phamclust-1.3.3.dist-info/RECORD
