Metadata-Version: 2.1
Name: phamclust
Version: 1.3.3
Summary: Cluster genomes based on gene phamily data
Home-page: https://github.com/chg60/phamclust
Author: Christian Gauthier
Author-email: chg60@pitt.edu
Project-URL: Source, https://github.com/chg60/phamclust
Classifier: Intended Audience :: Science/Research
Classifier: License :: OSI Approved :: GNU General Public License v3 (GPLv3)
Classifier: Operating System :: MacOS
Classifier: Operating System :: POSIX :: Linux
Classifier: Programming Language :: Python
Classifier: Programming Language :: Python :: 3
Classifier: Programming Language :: Python :: 3 :: Only
Classifier: Programming Language :: Python :: 3.6
Classifier: Programming Language :: Python :: 3.7
Classifier: Programming Language :: Python :: 3.8
Classifier: Programming Language :: Python :: 3.9
Classifier: Programming Language :: Python :: 3.10
Classifier: Programming Language :: Python :: 3.11
Requires-Python: >=3.6
License-File: LICENSE
Requires-Dist: joblib ~=1.4.0
Requires-Dist: kaleido ~=0.2.0
Requires-Dist: numpy ~=1.24.0
Requires-Dist: pandas ~=2.0.0
Requires-Dist: parasail ~=1.3.0
Requires-Dist: plotly ~=5.18.0
Requires-Dist: scikit-learn ~=1.3.0
Requires-Dist: scipy ~=1.10.0
